LICENSE
README.md
setup.cfg
setup.py
orvibo/__init__.py
orvibo/s20.py
orvibo.egg-info/PKG-INFO
orvibo.egg-info/SOURCES.txt
orvibo.egg-info/dependency_links.txt
orvibo.egg-info/top_level.txt