Metadata-Version: 2.1
Name: orvibo
Version: 1.1.2
Summary: Control Orvibo products.
Home-page: https://github.com/happyleavesaoc/python-orvibo/
Author: happyleaves
Author-email: happyleaves.tfr@gmail.com
License: MIT
Platform: UNKNOWN
Classifier: License :: OSI Approved :: MIT License
Classifier: Operating System :: OS Independent
Classifier: Programming Language :: Python :: 3
License-File: LICENSE
